{
  "partners": [
    {
      "id": "PAR001",
      "name": "Pedro Suarez Andrade",
      "image": "https://www.canr.msu.edu/contentAsset/image/abafcfa4-0293-4e9c-9d96-80f0caad1458/fileAsset/filter/Resize,Jpeg/resize_w/600/jpeg_q/100",
      "crea": "201908111520",
      "lasta": "201908111520",
      "tareasp": 1,
      "tareaspro": 5,
      "tareasok": 0
    },
    {
      "id": "PAR002",
      "name": "Moises Acevedo Cisneros",
      "image": "",
      "crea": "201908111520",
      "lasta": "201908111520",
      "tareasp": 10,
      "tareaspro": 3,
      "tareasok": 11
    },
    {
      "id": "PAR003",
      "name": "Adrián Cordero Torres",
      "image": "",
      "crea": "201908111520",
      "lasta": "201908111520",
      "tareasp": 10,
      "tareaspro": 1,
      "tareasok": 11
    },
    {
      "id": "PAR004",
      "name": "Mariana Sánchez Navarro",
      "image": "https://encrypted-tbn0.gstatic.com/images?q=tbn:ANd9GcRDev-tBrY5yUXGmiVfUiFAcGY4g5crNeq_o-i5EgicBxACODMUZw",
      "crea": "201908111520",
      "lasta": "201908111520",
      "tareasp": 10,
      "tareaspro": 0,
      "tareasok": 11
    },
    {
      "id": "PAR005",
      "name": "Mauricio Torres Méndez",
      "image": "https://encrypted-tbn0.gstatic.com/images?q=tbn:ANd9GcSmgSMoQlkbjglfyG8UTIa9AGBNbAUQ4Z22_gbdF6D6rTScYCanxQ",
      "crea": "201908111520",
      "lasta": "201908111520",
      "tareasp": 10,
      "tareaspro": 0,
      "tareasok": 11
    },
    {
      "id": "PAR006",
      "name": "Rocío López Victorino",
      "image": "https://s30428.pcdn.co/wp-content/uploads/2019/05/sweetcorn-1024x503.png",
      "crea": "201908111520",
      "lasta": "201908111520",
      "tareasp": 10,
      "tareaspro": 0,
      "tareasok": 11
    },
    {
      "id": "PAR007",
      "name": "José Cárdenas Mendoza",
      "image": "https://cdn.gardenista.com/wp-content/uploads/2018/04/jm-fortier-the-market-gardener-1.jpg",
      "crea": "201908111520",
      "lasta": "201908111520",
      "tareasp": 10,
      "tareaspro": 2,
      "tareasok": 11
    },
    {
      "id": "PAR008",
      "name": "Oscar Maldonado Quiróz",
      "image": "https://encrypted-tbn0.gstatic.com/images?q=tbn:ANd9GcQQdTSsFDIc-isCfNcG7z1VrbrPZoSbpIHiJlbu5JUP50klNmgGkw",
      "crea": "201908111520",
      "lasta": "201908111520",
      "tareasp": 10,
      "tareaspro": 0,
      "tareasok": 11
    },
    {
      "id": "PAR009",
      "name": "Sergio Dávalos Torres",
      "image": "https://encrypted-tbn0.gstatic.com/images?q=tbn:ANd9GcShKsQy8cN7xufndJ11CKiT69WaYLHrPS21pcjT1iKpjTxZS_mqVQ",
      "crea": "201908111520",
      "lasta": "201908111520",
      "tareasp": 10,
      "tareaspro": 0,
      "tareasok": 11
    },
    {
      "id": "PAR010",
      "name": "Antonio Torres López",
      "image": "https://encrypted-tbn0.gstatic.com/images?q=tbn:ANd9GcQlHBWkDBG8ON7PX0e46WXiZjOQzh-C57FYztHrn4pkrjsEPSHICw",
      "crea": "201908111520",
      "lasta": "201908111520",
      "tareasp": 10,
      "tareaspro": 8,
      "tareasok": 11
    }

  ]
}